{
  "parent": "minecraft:recipes/root",
  "criteria": {
    "has_crystal_block_cyan": {
      "conditions": {
        "items": [
          {
            "items": "groveextras:crystal_block_cyan"
          }
        ]
      },
      "trigger": "minecraft:inventory_changed"
    },
    "has_the_recipe": {
      "conditions": {
        "recipe": "minecraft:crystal_bricks_cyan_from_crystal_block_cyan_stonecutting"
      },
      "trigger": "minecraft:recipe_unlocked"
    }
  },
  "requirements": [
    [
      "has_the_recipe",
      "has_crystal_block_cyan"
    ]
  ],
  "rewards": {
    "recipes": [
      "minecraft:crystal_bricks_cyan_from_crystal_block_cyan_stonecutting"
    ]
  }
}